taskcli/__init__.py
taskcli/cli.py
taskcli_manager-1.0.0.dist-info/licenses/LICENSE
taskcli_manager-1.0.0.dist-info/METADATA
taskcli_manager-1.0.0.dist-info/WHEEL
taskcli_manager-1.0.0.dist-info/entry_points.txt
taskcli_manager-1.0.0.dist-info/top_level.txt
taskcli_manager-1.0.0.dist-info/RECORD
