Metadata-Version: 2.4
Name: taskcli-manager
Version: 1.0.0
Summary: Interactive CLI for TaskCLI - Manage your tasks from the terminal
Author-email: Ishita Tiwari <ishitatiwari1517@gmail.com>
License-Expression: MIT
Project-URL: Homepage, https://github.com/ishitatiwari1517/ojt_project_repo
Keywords: cli,task,todo,productivity,terminal
Classifier: Development Status :: 4 - Beta
Classifier: Environment :: Console
Classifier: Intended Audience :: End Users/Desktop
Classifier: Operating System :: OS Independent
Classifier: Programming Language :: Python :: 3
Classifier: Programming Language :: Python :: 3.8
Classifier: Programming Language :: Python :: 3.9
Classifier: Programming Language :: Python :: 3.10
Classifier: Programming Language :: Python :: 3.11
Classifier: Topic :: Utilities
Requires-Python: >=3.8
License-File: LICENSE
Requires-Dist: requests>=2.25.0
Dynamic: license-file
